lattis/__init__.py
lattis/__main__.py
lattis/cli.py
lattis/plugins.py
lattis/agents/__init__.py
lattis/agents/plugin.py
lattis/agents/registry.py
lattis/agents/builtins/__init__.py
lattis/agents/builtins/assistant.py
lattis/agents/builtins/poetry.py
lattis/client/__init__.py
lattis/client/api.py
lattis/client/inprocess.py
lattis/client/streaming.py
lattis/domain/__init__.py
lattis/domain/agents.py
lattis/domain/messages.py
lattis/domain/model_selection.py
lattis/domain/sessions.py
lattis/domain/threads.py
lattis/protocol/__init__.py
lattis/protocol/schemas.py
lattis/runtime/__init__.py
lattis/runtime/bootstrap.py
lattis/runtime/chat.py
lattis/runtime/context.py
lattis/runtime/thread_state.py
lattis/server/__init__.py
lattis/server/app.py
lattis/server/asgi.py
lattis/server/deps.py
lattis/server/routers/__init__.py
lattis/server/routers/agents.py
lattis/server/routers/meta.py
lattis/server/routers/models.py
lattis/server/routers/threads.py
lattis/server/routers/ui.py
lattis/settings/__init__.py
lattis/settings/env.py
lattis/settings/storage.py
lattis/storage/__init__.py
lattis/storage/sqlite.py
lattis/tui/__init__.py
lattis/tui/app.py
lattis/tui/commands.py
lattis/tui/rendering.py
lattis/tui/state.py
lattis/tui/widgets.py
lattis/web/__init__.py
lattis/web/static/index.html
lattis/web/static/assets/index-C1_N5cMR.css
lattis/web/static/assets/index-CW7u1B5o.js
lattis-0.6.1.dist-info/METADATA
lattis-0.6.1.dist-info/WHEEL
lattis-0.6.1.dist-info/entry_points.txt
lattis-0.6.1.dist-info/RECORD
