Metadata-Version: 2.4
Name: lattis
Version: 0.6.1
Summary: A pluggable agent toolkit (server + TUI + web UI)
Project-URL: Homepage, https://github.com/caesarnine/lattis
Project-URL: Repository, https://github.com/caesarnine/lattis
Project-URL: Issues, https://github.com/caesarnine/lattis/issues
License-Expression: MIT
Keywords: agent,ai,automation,bash,cli,llm,tools
Classifier: Development Status :: 3 - Alpha
Classifier: Environment :: Console
Classifier: Intended Audience :: Developers
Classifier: License :: OSI Approved :: MIT License
Classifier: Programming Language :: Python :: 3.12
Classifier: Topic :: Software Development :: Libraries :: Application Frameworks
Requires-Python: >=3.12
Requires-Dist: fastapi>=0.110.0
Requires-Dist: httpx>=0.27.0
Requires-Dist: pydantic-ai>=1.37.0
Requires-Dist: textual>=6.11.0
Requires-Dist: uvicorn>=0.30.0
Provides-Extra: lint
Requires-Dist: ruff>=0.9.0; extra == 'lint'
Provides-Extra: test
Requires-Dist: pytest>=8.0.0; extra == 'test'
